setup.py
nibbler/__init__.py
nibbler/parser.py
nibbler_python.egg-info/PKG-INFO
nibbler_python.egg-info/SOURCES.txt
nibbler_python.egg-info/dependency_links.txt
nibbler_python.egg-info/requires.txt
nibbler_python.egg-info/top_level.txt
test/__init__.py
test/test_parser.py